{"pages":[{"page":256,"annotations":[{"type":"Link","bounds":[264,318,32,30],"objref":"1699","action":{"type":"GoTo","page":1413,"zoom":"XYZ 116 389 0"}}]},{"page":769,"annotations":[{"type":"Link","bounds":[471,891,42,30],"objref":"4136","action":{"type":"GoTo","page":1418,"zoom":"XYZ 116 217 0"}}]},{"page":514,"annotations":[{"type":"Link","bounds":[555,180,42,31],"objref":"2816","action":{"type":"GoTo","page":1416,"zoom":"XYZ 116 378 0"}}]},{"page":260,"annotations":[{"type":"Link","bounds":[654,330,34,29],"objref":"1708","action":{"type":"GoTo","page":1413,"zoom":"XYZ 116 263 0"}},{"type":"Link","bounds":[443,651,32,29],"objref":"1709","action":{"type":"GoTo","page":1414,"zoom":"XYZ 116 1100 0"}},{"type":"Link","bounds":[319,834,34,29],"objref":"1710","action":{"type":"GoTo","page":1414,"zoom":"XYZ 116 1042 0"}}]},{"page":775,"annotations":[{"type":"Link","bounds":[154,180,42,31],"objref":"4149","action":{"type":"GoTo","page":1418,"zoom":"XYZ 116 160 0"}},{"type":"Link","bounds":[215,215,43,29],"objref":"4150","action":{"type":"GoTo","page":1419,"zoom":"XYZ 116 1100 0"}}]},{"page":1035,"annotations":[{"type":"Link","bounds":[767,432,43,31],"objref":"5483","action":{"type":"GoTo","page":1420,"zoom":"XYZ 116 951 0"}}]},{"page":779,"annotations":[{"type":"Link","bounds":[299,468,43,29],"objref":"4159","action":{"type":"GoTo","page":1419,"zoom":"XYZ 116 1042 0"}}]},{"page":267,"annotations":[{"type":"Link","bounds":[428,834,30,29],"objref":"1725","action":{"type":"GoTo","page":1414,"zoom":"XYZ 116 951 0"}}]},{"page":1044,"annotations":[{"type":"Link","bounds":[613,1028,44,31],"objref":"5503","action":{"type":"GoTo","page":1420,"zoom":"XYZ 116 893 0"}}]},{"page":1303,"annotations":[{"type":"Link","bounds":[344,215,43,29],"objref":"6375","action":{"type":"GoTo","page":1422,"zoom":"XYZ 116 550 0"}}]},{"page":25,"annotations":[{"type":"Link","bounds":[118,163,9,30],"objref":"462","action":{"type":"GoTo","page":-1}},{"type":"Link","bounds":[118,191,9,29],"objref":"463","action":{"type":"GoTo","page":-1}}]},{"page":26,"annotations":[{"type":"Link","bounds":[626,385,23,29],"objref":"558","action":{"type":"GoTo","page":1406,"zoom":"XYZ 116 930 0"}}]},{"page":540,"annotations":[{"type":"Link","bounds":[752,180,44,31],"objref":"3156","action":{"type":"GoTo","page":1416,"zoom":"XYZ 116 320 0"}}]},{"page":541,"annotations":[{"type":"Link","bounds":[168,524,43,31],"objref":"3159","action":{"type":"GoTo","page":1416,"zoom":"XYZ 116 229 0"}},{"type":"Link","bounds":[183,559,45,29],"objref":"3160","action":{"type":"GoTo","page":1417,"zoom":"XYZ 116 1100 0"}},{"type":"Link","bounds":[306,730,41,31],"objref":"3161","action":{"type":"GoTo","page":1417,"zoom":"XYZ 116 939 0"}}]},{"page":1061,"annotations":[{"type":"Link","bounds":[657,811,43,29],"objref":"5538","action":{"type":"GoTo","page":1420,"zoom":"XYZ 116 802 0"}}]},{"page":38,"annotations":[{"type":"Link","bounds":[533,834,23,29],"objref":"714","action":{"type":"GoTo","page":1406,"zoom":"XYZ 116 804 0"}},{"type":"Link","bounds":[287,903,23,29],"objref":"715","action":{"type":"GoTo","page":1406,"zoom":"XYZ 116 609 0"}}]},{"page":1063,"annotations":[{"type":"Link","bounds":[371,318,40,30],"objref":"5544","action":{"type":"GoTo","page":1420,"zoom":"XYZ 116 744 0"}},{"type":"Link","bounds":[637,318,41,30],"objref":"5545","action":{"type":"GoTo","page":1420,"zoom":"XYZ 116 687 0"}}]},{"page":40,"annotations":[{"type":"Link","bounds":[747,547,23,31],"objref":"720","action":{"type":"GoTo","page":1406,"zoom":"XYZ 116 483 0"}}]},{"page":297,"annotations":[{"type":"Link","bounds":[521,399,34,29],"objref":"1786","action":{"type":"GoTo","page":1414,"zoom":"XYZ 116 893 0"}}]},{"page":1322,"annotations":[{"type":"Link","bounds":[475,972,41,29],"objref":"6415","action":{"type":"GoTo","page":1422,"zoom":"XYZ 116 423 0"}}]},{"page":1323,"annotations":[{"type":"Link","bounds":[768,1005,42,31],"objref":"6418","action":{"type":"GoTo","page":1422,"zoom":"XYZ 116 366 0"}}]},{"page":43,"annotations":[{"type":"Link","bounds":[159,822,23,31],"objref":"727","action":{"type":"GoTo","page":1406,"zoom":"XYZ 116 426 0"}}]},{"page":557,"annotations":[{"type":"Link","bounds":[390,903,39,29],"objref":"3194","action":{"type":"GoTo","page":1417,"zoom":"XYZ 116 847 0"}}]},{"page":50,"annotations":[{"type":"Link","bounds":[677,400,44,32],"objref":"743","action":{"type":"GoTo","page":1406,"zoom":"XYZ 116 300 0"}},{"type":"Link","bounds":[228,900,23,29],"objref":"744","action":{"type":"GoTo","page":1406,"zoom":"XYZ 116 242 0"}}]},{"page":821,"annotations":[{"type":"Link","bounds":[157,215,43,29],"objref":"4534","action":{"type":"GoTo","page":1419,"zoom":"XYZ 116 985 0"}},{"type":"Link","bounds":[741,593,43,30],"objref":"4535","action":{"type":"GoTo","page":1419,"zoom":"XYZ 116 893 0"}}]},{"page":56,"annotations":[{"type":"Link","bounds":[535,674,23,29],"objref":"757","action":{"type":"GoTo","page":1407,"zoom":"XYZ 116 1008 0"}}]},{"page":827,"annotations":[{"type":"Link","bounds":[478,697,43,29],"objref":"4549","action":{"type":"GoTo","page":1419,"zoom":"XYZ 116 836 0"}}]},{"page":60,"annotations":[{"type":"Link","bounds":[280,490,23,29],"objref":"767","action":{"type":"GoTo","page":1407,"zoom":"XYZ 116 882 0"}},{"type":"Link","bounds":[501,662,32,30],"objref":"768","action":{"type":"GoTo","page":1407,"zoom":"XYZ 116 756 0"}}]},{"page":317,"annotations":[{"type":"Link","bounds":[785,926,32,29],"objref":"2148","action":{"type":"GoTo","page":1414,"zoom":"XYZ 116 836 0"}}]},{"page":318,"annotations":[{"type":"Link","bounds":[649,1018,35,29],"objref":"2151","action":{"type":"GoTo","page":1414,"zoom":"XYZ 116 779 0"}}]},{"page":62,"annotations":[{"type":"Link","bounds":[726,662,30,30],"objref":"773","action":{"type":"GoTo","page":1407,"zoom":"XYZ 116 630 0"}}]},{"page":63,"annotations":[{"type":"Link","bounds":[785,1028,32,31],"objref":"776","action":{"type":"GoTo","page":1407,"zoom":"XYZ 116 572 0"}}]},{"page":64,"annotations":[{"type":"Link","bounds":[458,914,34,30],"objref":"780","action":{"type":"GoTo","page":1407,"zoom":"XYZ 116 515 0"}}]},{"page":65,"annotations":[{"type":"Link","bounds":[197,215,32,29],"objref":"783","action":{"type":"GoTo","page":1407,"zoom":"XYZ 116 423 0"}}]},{"page":68,"annotations":[{"type":"Link","bounds":[785,959,32,31],"objref":"790","action":{"type":"GoTo","page":1407,"zoom":"XYZ 116 366 0"}}]},{"page":590,"annotations":[{"type":"Link","bounds":[379,949,40,29],"objref":"3261","action":{"type":"GoTo","page":1417,"zoom":"XYZ 116 790 0"}},{"type":"Link","bounds":[498,982,40,31],"objref":"3262","action":{"type":"GoTo","page":1417,"zoom":"XYZ 116 698 0"}}]},{"page":592,"annotations":[{"type":"Link","bounds":[275,249,41,31],"objref":"3267","action":{"type":"GoTo","page":1417,"zoom":"XYZ 116 538 0"}}]},{"page":80,"annotations":[{"type":"Link","bounds":[118,526,32,29],"objref":"1021","action":{"type":"GoTo","page":1408,"zoom":"XYZ 116 1100 0"}},{"type":"Link","bounds":[403,640,31,29],"objref":"1022","action":{"type":"GoTo","page":1408,"zoom":"XYZ 116 1008 0"}}]},{"page":81,"annotations":[{"type":"Link","bounds":[417,982,32,31],"objref":"1025","action":{"type":"GoTo","page":1408,"zoom":"XYZ 116 951 0"}}]},{"page":850,"annotations":[{"type":"Link","bounds":[414,834,43,29],"objref":"4598","action":{"type":"GoTo","page":1419,"zoom":"XYZ 116 779 0"}}]},{"page":853,"annotations":[{"type":"Link","bounds":[767,376,43,29],"objref":"4605","action":{"type":"GoTo","page":1419,"zoom":"XYZ 116 721 0"}}]},{"page":342,"annotations":[{"type":"Link","bounds":[755,180,33,31],"objref":"2202","action":{"type":"GoTo","page":1414,"zoom":"XYZ 116 653 0"}},{"type":"Link","bounds":[290,720,34,29],"objref":"2203","action":{"type":"GoTo","page":1414,"zoom":"XYZ 116 595 0"}}]},{"page":86,"annotations":[{"type":"Link","bounds":[778,1063,32,29],"objref":"1036","action":{"type":"GoTo","page":1408,"zoom":"XYZ 116 825 0"}}]},{"page":599,"annotations":[{"type":"Link","bounds":[732,966,41,29],"objref":"3546","action":{"type":"GoTo","page":1417,"zoom":"XYZ 116 412 0"}}]},{"page":87,"annotations":[{"type":"Link","bounds":[744,215,34,29],"objref":"1039","action":{"type":"GoTo","page":1408,"zoom":"XYZ 116 698 0"}}]},{"page":88,"annotations":[{"type":"Link","bounds":[211,1028,32,31],"objref":"1042","action":{"type":"GoTo","page":1408,"zoom":"XYZ 116 641 0"}}]},{"page":89,"annotations":[{"type":"Link","bounds":[512,215,33,31],"objref":"1045","action":{"type":"GoTo","page":1408,"zoom":"XYZ 116 584 0"}},{"type":"Link","bounds":[315,697,33,30],"objref":"1046","action":{"type":"GoTo","page":1408,"zoom":"XYZ 116 492 0"}}]},{"page":90,"annotations":[{"type":"Link","bounds":[263,422,33,29],"objref":"1049","action":{"type":"GoTo","page":1408,"zoom":"XYZ 116 401 0"}},{"type":"Link","bounds":[339,628,34,29],"objref":"1050","action":{"type":"GoTo","page":1408,"zoom":"XYZ 116 309 0"}},{"type":"Link","bounds":[226,697,34,29],"objref":"1051","action":{"type":"GoTo","page":1408,"zoom":"XYZ 116 217 0"}},{"type":"Link","bounds":[159,903,32,29],"objref":"1052","action":{"type":"GoTo","page":1409,"zoom":"XYZ 116 1100 0"}}]},{"page":95,"annotations":[{"type":"Link","bounds":[451,1028,33,31],"objref":"1063","action":{"type":"GoTo","page":1409,"zoom":"XYZ 116 847 0"}}]},{"page":870,"annotations":[{"type":"Link","bounds":[469,674,43,29],"objref":"4640","action":{"type":"GoTo","page":1419,"zoom":"XYZ 116 630 0"}}]},{"page":614,"annotations":[{"type":"Link","bounds":[649,341,42,30],"objref":"3579","action":{"type":"GoTo","page":1417,"zoom":"XYZ 116 355 0"}}]},{"page":105,"annotations":[{"type":"Link","bounds":[295,341,33,30],"objref":"1084","action":{"type":"GoTo","page":1409,"zoom":"XYZ 116 653 0"}},{"type":"Link","bounds":[782,799,34,31],"objref":"1085","action":{"type":"GoTo","page":1409,"zoom":"XYZ 116 595 0"}}]},{"page":106,"annotations":[{"type":"Link","bounds":[429,949,32,29],"objref":"1088","action":{"type":"GoTo","page":1409,"zoom":"XYZ 116 538 0"}}]},{"page":363,"annotations":[{"type":"Link","bounds":[674,559,33,29],"objref":"2248","action":{"type":"GoTo","page":1414,"zoom":"XYZ 116 538 0"}}]},{"page":114,"annotations":[{"type":"Link","bounds":[287,891,32,30],"objref":"1105","action":{"type":"GoTo","page":1409,"zoom":"XYZ 116 481 0"}}]},{"page":1145,"annotations":[{"type":"Link","bounds":[429,112,42,30],"objref":"5710","action":{"type":"GoTo","page":1420,"zoom":"XYZ 116 630 0"}}]},{"page":377,"annotations":[{"type":"Link","bounds":[584,788,32,29],"objref":"2277","action":{"type":"GoTo","page":1414,"zoom":"XYZ 116 481 0"}}]},{"page":1148,"annotations":[{"type":"Link","bounds":[365,307,43,29],"objref":"5717","action":{"type":"GoTo","page":1420,"zoom":"XYZ 116 572 0"}}]},{"page":1149,"annotations":[{"type":"Link","bounds":[703,513,43,29],"objref":"5720","action":{"type":"GoTo","page":1420,"zoom":"XYZ 116 515 0"}},{"type":"Link","bounds":[267,582,43,29],"objref":"5721","action":{"type":"GoTo","page":1420,"zoom":"XYZ 116 458 0"}}]},{"page":1406,"annotations":[{"type":"Link","bounds":[188,281,23,31],"objref":"7407","action":{"type":"GoTo","page":26,"zoom":"XYZ 624 825 0"}},{"type":"Link","bounds":[188,408,23,30],"objref":"7408","action":{"type":"GoTo","page":38,"zoom":"XYZ 532 375 0"}},{"type":"Link","bounds":[188,603,23,30],"objref":"7409","action":{"type":"GoTo","page":38,"zoom":"XYZ 286 307 0"}},{"type":"Link","bounds":[188,729,23,30],"objref":"7410","action":{"type":"GoTo","page":40,"zoom":"XYZ 745 662 0"}},{"type":"Link","bounds":[188,787,23,29],"objref":"7411","action":{"type":"GoTo","page":43,"zoom":"XYZ 158 387 0"}},{"type":"Link","bounds":[188,912,23,31],"objref":"7412","action":{"type":"GoTo","page":50,"zoom":"XYZ 674 810 0"}},{"type":"Link","bounds":[188,970,23,29],"objref":"7413","action":{"type":"GoTo","page":50,"zoom":"XYZ 226 310 0"}}]},{"page":126,"annotations":[{"type":"Link","bounds":[752,399,35,29],"objref":"1130","action":{"type":"GoTo","page":1409,"zoom":"XYZ 116 423 0"}}]},{"page":1407,"annotations":[{"type":"Link","bounds":[188,203,23,31],"objref":"7416","action":{"type":"GoTo","page":56,"zoom":"XYZ 532 536 0"}},{"type":"Link","bounds":[188,330,23,29],"objref":"7417","action":{"type":"GoTo","page":60,"zoom":"XYZ 278 719 0"}},{"type":"Link","bounds":[188,455,32,31],"objref":"7418","action":{"type":"GoTo","page":60,"zoom":"XYZ 499 547 0"}},{"type":"Link","bounds":[188,582,30,29],"objref":"7419","action":{"type":"GoTo","page":62,"zoom":"XYZ 725 547 0"}},{"type":"Link","bounds":[188,640,32,29],"objref":"7420","action":{"type":"GoTo","page":63,"zoom":"XYZ 783 181 0"}},{"type":"Link","bounds":[188,697,32,30],"objref":"7421","action":{"type":"GoTo","page":64,"zoom":"XYZ 458 295 0"}},{"type":"Link","bounds":[188,788,32,31],"objref":"7422","action":{"type":"GoTo","page":65,"zoom":"XYZ 197 994 0"}},{"type":"Link","bounds":[188,846,32,29],"objref":"7423","action":{"type":"GoTo","page":68,"zoom":"XYZ 783 249 0"}}]},{"page":1151,"annotations":[{"type":"Link","bounds":[755,765,43,29],"objref":"5726","action":{"type":"GoTo","page":1420,"zoom":"XYZ 116 401 0"}}]},{"page":383,"annotations":[{"type":"Link","bounds":[371,914,35,30],"objref":"2290","action":{"type":"GoTo","page":1414,"zoom":"XYZ 116 423 0"}}]},{"page":1408,"annotations":[{"type":"Link","bounds":[188,112,32,30],"objref":"7426","action":{"type":"GoTo","page":80,"zoom":"XYZ 116 685 0"}},{"type":"Link","bounds":[188,203,32,31],"objref":"7427","action":{"type":"GoTo","page":80,"zoom":"XYZ 402 570 0"}},{"type":"Link","bounds":[188,261,32,29],"objref":"7428","action":{"type":"GoTo","page":81,"zoom":"XYZ 417 226 0"}},{"type":"Link","bounds":[188,387,32,30],"objref":"7429","action":{"type":"GoTo","page":86,"zoom":"XYZ 776 146 0"}},{"type":"Link","bounds":[188,513,34,29],"objref":"7430","action":{"type":"GoTo","page":87,"zoom":"XYZ 742 994 0"}},{"type":"Link","bounds":[188,570,32,30],"objref":"7431","action":{"type":"GoTo","page":88,"zoom":"XYZ 210 181 0"}},{"type":"Link","bounds":[188,628,34,29],"objref":"7432","action":{"type":"GoTo","page":89,"zoom":"XYZ 511 994 0"}},{"type":"Link","bounds":[188,720,34,29],"objref":"7433","action":{"type":"GoTo","page":89,"zoom":"XYZ 313 513 0"}},{"type":"Link","bounds":[188,811,34,29],"objref":"7434","action":{"type":"GoTo","page":90,"zoom":"XYZ 261 788 0"}},{"type":"Link","bounds":[188,903,34,29],"objref":"7435","action":{"type":"GoTo","page":90,"zoom":"XYZ 339 582 0"}},{"type":"Link","bounds":[188,995,34,29],"objref":"7436","action":{"type":"GoTo","page":90,"zoom":"XYZ 225 513 0"}}]},{"page":1152,"annotations":[{"type":"Link","bounds":[533,112,43,30],"objref":"5729","action":{"type":"GoTo","page":1420,"zoom":"XYZ 116 309 0"}}]},{"page":1409,"annotations":[{"type":"Link","bounds":[188,112,34,30],"objref":"7439","action":{"type":"GoTo","page":90,"zoom":"XYZ 156 307 0"}},{"type":"Link","bounds":[188,365,34,29],"objref":"7440","action":{"type":"GoTo","page":95,"zoom":"XYZ 450 181 0"}},{"type":"Link","bounds":[188,559,34,31],"objref":"7441","action":{"type":"GoTo","page":105,"zoom":"XYZ 294 868 0"}},{"type":"Link","bounds":[188,617,34,29],"objref":"7442","action":{"type":"GoTo","page":105,"zoom":"XYZ 782 410 0"}},{"type":"Link","bounds":[188,674,32,30],"objref":"7443","action":{"type":"GoTo","page":106,"zoom":"XYZ 428 261 0"}},{"type":"Link","bounds":[188,732,34,29],"objref":"7444","action":{"type":"GoTo","page":114,"zoom":"XYZ 285 318 0"}},{"type":"Link","bounds":[188,788,34,31],"objref":"7445","action":{"type":"GoTo","page":126,"zoom":"XYZ 751 811 0"}},{"type":"Link","bounds":[188,949,34,30],"objref":"7446","action":{"type":"GoTo","page":134,"zoom":"XYZ 663 857 0"}}]},{"page":1410,"annotations":[{"type":"Link","bounds":[188,203,34,31],"objref":"7450","action":{"type":"GoTo","page":135,"zoom":"XYZ 554 1028 0"}},{"type":"Link","bounds":[188,295,34,30],"objref":"7451","action":{"type":"GoTo","page":135,"zoom":"XYZ 366 834 0"}},{"type":"Link","bounds":[188,422,32,29],"objref":"7452","action":{"type":"GoTo","page":135,"zoom":"XYZ 742 238 0"}},{"type":"Link","bounds":[188,513,34,29],"objref":"7453","action":{"type":"GoTo","page":143,"zoom":"XYZ 448 662 0"}},{"type":"Link","bounds":[188,707,34,31],"objref":"7454","action":{"type":"GoTo","page":144,"zoom":"XYZ 331 284 0"}},{"type":"Link","bounds":[188,799,34,31],"objref":"7455","action":{"type":"GoTo","page":149,"zoom":"XYZ 700 696 0"}},{"type":"Link","bounds":[188,995,34,29],"objref":"7456","action":{"type":"GoTo","page":151,"zoom":"XYZ 545 215 0"}}]},{"page":1154,"annotations":[{"type":"Link","bounds":[775,261,42,29],"objref":"5734","action":{"type":"GoTo","page":1420,"zoom":"XYZ 116 252 0"}}]},{"page":1411,"annotations":[{"type":"Link","bounds":[188,112,34,30],"objref":"7459","action":{"type":"GoTo","page":169,"zoom":"XYZ 586 467 0"}},{"type":"Link","bounds":[188,203,34,31],"objref":"7460","action":{"type":"GoTo","page":175,"zoom":"XYZ 293 994 0"}},{"type":"Link","bounds":[188,261,34,29],"objref":"7461","action":{"type":"GoTo","page":175,"zoom":"XYZ 587 582 0"}},{"type":"Link","bounds":[188,353,34,29],"objref":"7462","action":{"type":"GoTo","page":175,"zoom":"XYZ 695 547 0"}},{"type":"Link","bounds":[188,445,34,29],"objref":"7463","action":{"type":"GoTo","page":175,"zoom":"XYZ 257 513 0"}},{"type":"Link","bounds":[188,501,34,31],"objref":"7464","action":{"type":"GoTo","page":176,"zoom":"XYZ 344 685 0"}},{"type":"Link","bounds":[188,593,34,30],"objref":"7465","action":{"type":"GoTo","page":178,"zoom":"XYZ 225 960 0"}},{"type":"Link","bounds":[188,651,34,29],"objref":"7466","action":{"type":"GoTo","page":178,"zoom":"XYZ 158 330 0"}},{"type":"Link","bounds":[188,880,34,29],"objref":"7467","action":{"type":"GoTo","page":193,"zoom":"XYZ 782 1097 0"}},{"type":"Link","bounds":[188,937,32,30],"objref":"7468","action":{"type":"GoTo","page":203,"zoom":"XYZ 553 616 0"}},{"type":"Link","bounds":[188,995,34,29],"objref":"7469","action":{"type":"GoTo","page":203,"zoom":"XYZ 404 513 0"}}]},{"page":1155,"annotations":[{"type":"Link","bounds":[443,730,43,31],"objref":"5737","action":{"type":"GoTo","page":1420,"zoom":"XYZ 116 194 0"}}]},{"page":1412,"annotations":[{"type":"Link","bounds":[188,112,34,30],"objref":"7473","action":{"type":"GoTo","page":204,"zoom":"XYZ 603 708 0"}},{"type":"Link","bounds":[188,205,34,29],"objref":"7474","action":{"type":"GoTo","page":206,"zoom":"XYZ 720 536 0"}},{"type":"Link","bounds":[188,296,34,29],"objref":"7475","action":{"type":"GoTo","page":207,"zoom":"XYZ 632 719 0"}},{"type":"Link","bounds":[188,388,34,29],"objref":"7476","action":{"type":"GoTo","page":207,"zoom":"XYZ 467 375 0"}},{"type":"Link","bounds":[188,445,32,30],"objref":"7477","action":{"type":"GoTo","page":207,"zoom":"XYZ 616 181 0"}},{"type":"Link","bounds":[188,605,34,31],"objref":"7478","action":{"type":"GoTo","page":208,"zoom":"XYZ 209 994 0"}},{"type":"Link","bounds":[188,697,34,30],"objref":"7479","action":{"type":"GoTo","page":208,"zoom":"XYZ 483 742 0"}},{"type":"Link","bounds":[188,788,34,31],"objref":"7480","action":{"type":"GoTo","page":208,"zoom":"XYZ 513 375 0"}},{"type":"Link","bounds":[188,949,30,30],"objref":"7481","action":{"type":"GoTo","page":209,"zoom":"XYZ 380 444 0"}},{"type":"Link","bounds":[188,1040,34,31],"objref":"7482","action":{"type":"GoTo","page":210,"zoom":"XYZ 375 765 0"}}]},{"page":1156,"annotations":[{"type":"Link","bounds":[310,341,41,30],"objref":"5740","action":{"type":"GoTo","page":1421,"zoom":"XYZ 116 1100 0"}}]},{"page":1413,"annotations":[{"type":"Link","bounds":[188,112,34,30],"objref":"7485","action":{"type":"GoTo","page":210,"zoom":"XYZ 781 318 0"}},{"type":"Link","bounds":[188,170,34,29],"objref":"7486","action":{"type":"GoTo","page":211,"zoom":"XYZ 631 501 0"}},{"type":"Link","bounds":[188,364,34,30],"objref":"7487","action":{"type":"GoTo","page":213,"zoom":"XYZ 635 410 0"}},{"type":"Link","bounds":[188,490,34,29],"objref":"7488","action":{"type":"GoTo","page":239,"zoom":"XYZ 276 937 0"}},{"type":"Link","bounds":[188,547,32,31],"objref":"7489","action":{"type":"GoTo","page":239,"zoom":"XYZ 195 364 0"}},{"type":"Link","bounds":[188,674,34,29],"objref":"7490","action":{"type":"GoTo","page":241,"zoom":"XYZ 561 410 0"}},{"type":"Link","bounds":[188,730,34,31],"objref":"7491","action":{"type":"GoTo","page":255,"zoom":"XYZ 514 295 0"}},{"type":"Link","bounds":[188,822,34,31],"objref":"7492","action":{"type":"GoTo","page":256,"zoom":"XYZ 263 891 0"}},{"type":"Link","bounds":[188,949,32,29],"objref":"7493","action":{"type":"GoTo","page":260,"zoom":"XYZ 654 880 0"}}]},{"page":1157,"annotations":[{"type":"Link","bounds":[626,972,42,29],"objref":"5743","action":{"type":"GoTo","page":1421,"zoom":"XYZ 116 1008 0"}}]},{"page":1414,"annotations":[{"type":"Link","bounds":[188,112,34,30],"objref":"7496","action":{"type":"GoTo","page":260,"zoom":"XYZ 441 559 0"}},{"type":"Link","bounds":[188,170,34,29],"objref":"7497","action":{"type":"GoTo","page":260,"zoom":"XYZ 319 375 0"}},{"type":"Link","bounds":[188,261,30,29],"objref":"7498","action":{"type":"GoTo","page":267,"zoom":"XYZ 426 375 0"}},{"type":"Link","bounds":[188,318,34,30],"objref":"7499","action":{"type":"GoTo","page":297,"zoom":"XYZ 520 811 0"}},{"type":"Link","bounds":[188,376,30,29],"objref":"7500","action":{"type":"GoTo","page":317,"zoom":"XYZ 784 284 0"}},{"type":"Link","bounds":[188,432,34,31],"objref":"7501","action":{"type":"GoTo","page":318,"zoom":"XYZ 649 192 0"}},{"type":"Link","bounds":[188,559,34,29],"objref":"7502","action":{"type":"GoTo","page":342,"zoom":"XYZ 753 1028 0"}},{"type":"Link","bounds":[188,616,34,30],"objref":"7503","action":{"type":"GoTo","page":342,"zoom":"XYZ 289 490 0"}},{"type":"Link","bounds":[188,674,34,29],"objref":"7504","action":{"type":"GoTo","page":363,"zoom":"XYZ 673 650 0"}},{"type":"Link","bounds":[188,730,32,31],"objref":"7505","action":{"type":"GoTo","page":377,"zoom":"XYZ 582 421 0"}},{"type":"Link","bounds":[188,788,34,29],"objref":"7506","action":{"type":"GoTo","page":383,"zoom":"XYZ 371 295 0"}},{"type":"Link","bounds":[188,845,34,30],"objref":"7507","action":{"type":"GoTo","page":392,"zoom":"XYZ 684 788 0"}},{"type":"Link","bounds":[188,937,34,30],"objref":"7508"},{"type":"Link","bounds":[188,995,34,29],"objref":"7509","action":{"type":"GoTo","page":400,"zoom":"XYZ 462 375 0"}},{"type":"Link","bounds":[188,1051,34,31],"objref":"7510","action":{"type":"GoTo","page":401,"zoom":"XYZ 352 902 0"}}]},{"page":134,"annotations":[{"type":"Link","bounds":[663,353,34,29],"objref":"1148","action":{"type":"GoTo","page":1409,"zoom":"XYZ 116 263 0"}}]},{"page":1415,"annotations":[{"type":"Link","bounds":[188,112,32,30],"objref":"7513","action":{"type":"GoTo","page":409,"zoom":"XYZ 311 192 0"}},{"type":"Link","bounds":[188,170,34,29],"objref":"7514","action":{"type":"GoTo","page":416,"zoom":"XYZ 545 1063 0"}},{"type":"Link","bounds":[188,226,34,31],"objref":"7515","action":{"type":"GoTo","page":432,"zoom":"XYZ 359 501 0"}},{"type":"Link","bounds":[188,318,34,30],"objref":"7516","action":{"type":"GoTo","page":434,"zoom":"XYZ 165 1097 0"}},{"type":"Link","bounds":[188,445,32,29],"objref":"7517","action":{"type":"GoTo","page":443,"zoom":"XYZ 434 795 0"}},{"type":"Link","bounds":[188,536,34,29],"objref":"7518","action":{"type":"GoTo","page":451,"zoom":"XYZ 218 994 0"}},{"type":"Link","bounds":[188,628,34,29],"objref":"7519","action":{"type":"GoTo","page":453,"zoom":"XYZ 284 1097 0"}},{"type":"Link","bounds":[188,720,32,29],"objref":"7520","action":{"type":"GoTo","page":453,"zoom":"XYZ 332 1028 0"}},{"type":"Link","bounds":[188,776,34,31],"objref":"7521","action":{"type":"GoTo","page":460,"zoom":"XYZ 661 451 0"}},{"type":"Link","bounds":[188,834,34,29],"objref":"7522","action":{"type":"GoTo","page":460,"zoom":"XYZ 192 279 0"}},{"type":"Link","bounds":[188,926,34,29],"objref":"7523","action":{"type":"GoTo","page":461,"zoom":"XYZ 380 410 0"}},{"type":"Link","bounds":[188,982,34,31],"objref":"7524","action":{"type":"GoTo","page":464,"zoom":"XYZ 198 1063 0"}}]},{"page":135,"annotations":[{"type":"Link","bounds":[556,180,34,31],"objref":"1151","action":{"type":"GoTo","page":1410,"zoom":"XYZ 116 1008 0"}},{"type":"Link","bounds":[368,376,34,29],"objref":"1152","action":{"type":"GoTo","page":1410,"zoom":"XYZ 116 916 0"}},{"type":"Link","bounds":[744,972,32,29],"objref":"1153","action":{"type":"GoTo","page":1410,"zoom":"XYZ 116 790 0"}}]},{"page":1416,"annotations":[{"type":"Link","bounds":[188,112,34,30],"objref":"7527","action":{"type":"GoTo","page":464,"zoom":"XYZ 761 547 0"}},{"type":"Link","bounds":[188,203,43,31],"objref":"7528","action":{"type":"GoTo","page":466,"zoom":"XYZ 344 387 0"}},{"type":"Link","bounds":[188,295,41,30],"objref":"7529","action":{"type":"GoTo","page":474,"zoom":"XYZ 470 925 0"}},{"type":"Link","bounds":[188,387,43,30],"objref":"7530","action":{"type":"GoTo","page":483,"zoom":"XYZ 138 925 0"}},{"type":"Link","bounds":[188,547,43,31],"objref":"7531","action":{"type":"GoTo","page":483,"zoom":"XYZ 457 238 0"}},{"type":"Link","bounds":[188,639,43,30],"objref":"7532","action":{"type":"GoTo","page":491,"zoom":"XYZ 602 891 0"}},{"type":"Link","bounds":[188,834,43,29],"objref":"7533","action":{"type":"GoTo","page":514,"zoom":"XYZ 553 1028 0"}},{"type":"Link","bounds":[188,891,43,30],"objref":"7534","action":{"type":"GoTo","page":540,"zoom":"XYZ 751 1028 0"}},{"type":"Link","bounds":[188,982,43,31],"objref":"7535","action":{"type":"GoTo","page":541,"zoom":"XYZ 167 685 0"}}]},{"page":392,"annotations":[{"type":"Link","bounds":[684,422,34,29],"objref":"2309","action":{"type":"GoTo","page":1414,"zoom":"XYZ 116 366 0"}}]},{"page":1417,"annotations":[{"type":"Link","bounds":[188,112,43,30],"objref":"7538","action":{"type":"GoTo","page":541,"zoom":"XYZ 183 650 0"}},{"type":"Link","bounds":[188,272,43,31],"objref":"7539","action":{"type":"GoTo","page":541,"zoom":"XYZ 303 478 0"}},{"type":"Link","bounds":[188,364,40,30],"objref":"7540","action":{"type":"GoTo","page":557,"zoom":"XYZ 388 307 0"}},{"type":"Link","bounds":[188,422,40,29],"objref":"7541","action":{"type":"GoTo","page":590,"zoom":"XYZ 378 261 0"}},{"type":"Link","bounds":[188,513,40,29],"objref":"7542","action":{"type":"GoTo","page":590,"zoom":"XYZ 497 226 0"}},{"type":"Link","bounds":[188,674,40,29],"objref":"7543","action":{"type":"GoTo","page":592,"zoom":"XYZ 275 960 0"}},{"type":"Link","bounds":[188,799,40,31],"objref":"7544","action":{"type":"GoTo","page":599,"zoom":"XYZ 731 245 0"}},{"type":"Link","bounds":[188,857,40,29],"objref":"7545","action":{"type":"GoTo","page":614,"zoom":"XYZ 648 868 0"}},{"type":"Link","bounds":[188,1051,40,31],"objref":"7546","action":{"type":"GoTo","page":656,"zoom":"XYZ 537 834 0"}}]},{"page":1418,"annotations":[{"type":"Link","bounds":[188,112,40,30],"objref":"7549","action":{"type":"GoTo","page":666,"zoom":"XYZ 402 169 0"}},{"type":"Link","bounds":[188,170,40,29],"objref":"7550","action":{"type":"GoTo","page":672,"zoom":"XYZ 221 478 0"}},{"type":"Link","bounds":[188,226,40,31],"objref":"7551","action":{"type":"GoTo","page":673,"zoom":"XYZ 321 1028 0"}},{"type":"Link","bounds":[188,284,43,31],"objref":"7552","action":{"type":"GoTo","page":700,"zoom":"XYZ 284 925 0"}},{"type":"Link","bounds":[188,342,41,29],"objref":"7553","action":{"type":"GoTo","page":703,"zoom":"XYZ 739 524 0"}},{"type":"Link","bounds":[188,503,43,29],"objref":"7554","action":{"type":"GoTo","page":726,"zoom":"XYZ 773 467 0"}},{"type":"Link","bounds":[188,559,43,31],"objref":"7555","action":{"type":"GoTo","page":756,"zoom":"XYZ 265 673 0"}},{"type":"Link","bounds":[188,617,43,29],"objref":"7556","action":{"type":"GoTo","page":757,"zoom":"XYZ 639 845 0"}},{"type":"Link","bounds":[188,674,43,30],"objref":"7557","action":{"type":"GoTo","page":763,"zoom":"XYZ 514 971 0"}},{"type":"Link","bounds":[188,732,43,29],"objref":"7558","action":{"type":"GoTo","page":763,"zoom":"XYZ 326 330 0"}},{"type":"Link","bounds":[188,788,43,31],"objref":"7559","action":{"type":"GoTo","page":764,"zoom":"XYZ 370 1006 0"}},{"type":"Link","bounds":[188,880,43,31],"objref":"7560","action":{"type":"GoTo","page":765,"zoom":"XYZ 255 272 0"}},{"type":"Link","bounds":[188,938,43,29],"objref":"7561","action":{"type":"GoTo","page":767,"zoom":"XYZ 541 238 0"}},{"type":"Link","bounds":[188,995,43,30],"objref":"7562","action":{"type":"GoTo","page":769,"zoom":"XYZ 469 318 0"}},{"type":"Link","bounds":[188,1053,41,29],"objref":"7563","action":{"type":"GoTo","page":775,"zoom":"XYZ 154 1028 0"}}]},{"page":1162,"annotations":[{"type":"Link","bounds":[700,914,43,30],"objref":"5754","action":{"type":"GoTo","page":1421,"zoom":"XYZ 116 951 0"}}]},{"page":1419,"annotations":[{"type":"Link","bounds":[188,112,43,30],"objref":"7566","action":{"type":"GoTo","page":775,"zoom":"XYZ 214 994 0"}},{"type":"Link","bounds":[188,170,43,29],"objref":"7567","action":{"type":"GoTo","page":779,"zoom":"XYZ 299 742 0"}},{"type":"Link","bounds":[188,226,43,31],"objref":"7568","action":{"type":"GoTo","page":821,"zoom":"XYZ 155 994 0"}},{"type":"Link","bounds":[188,318,43,30],"objref":"7569","action":{"type":"GoTo","page":821,"zoom":"XYZ 741 616 0"}},{"type":"Link","bounds":[188,376,43,29],"objref":"7570","action":{"type":"GoTo","page":827,"zoom":"XYZ 476 513 0"}},{"type":"Link","bounds":[188,432,41,31],"objref":"7571","action":{"type":"GoTo","page":850,"zoom":"XYZ 412 375 0"}},{"type":"Link","bounds":[188,490,43,29],"objref":"7572","action":{"type":"GoTo","page":853,"zoom":"XYZ 766 834 0"}},{"type":"Link","bounds":[188,582,43,29],"objref":"7573","action":{"type":"GoTo","page":870,"zoom":"XYZ 468 536 0"}},{"type":"Link","bounds":[188,639,43,30],"objref":"7574","action":{"type":"GoTo","page":924,"zoom":"XYZ 588 971 0"}},{"type":"Link","bounds":[188,697,43,29],"objref":"7575","action":{"type":"GoTo","page":931,"zoom":"XYZ 718 531 0"}},{"type":"Link","bounds":[188,788,43,29],"objref":"7576","action":{"type":"GoTo","page":948,"zoom":"XYZ 440 203 0"}},{"type":"Link","bounds":[188,914,43,30],"objref":"7577","action":{"type":"GoTo","page":990,"zoom":"XYZ 586 868 0"}},{"type":"Link","bounds":[188,972,43,29],"objref":"7578","action":{"type":"GoTo","page":1001,"zoom":"XYZ 486 444 0"}},{"type":"Link","bounds":[188,1028,43,31],"objref":"7579","action":{"type":"GoTo","page":1002,"zoom":"XYZ 292 868 0"}}]},{"page":1163,"annotations":[{"type":"Link","bounds":[273,697,42,29],"objref":"5757","action":{"type":"GoTo","page":1421,"zoom":"XYZ 116 893 0"}}]},{"page":1420,"annotations":[{"type":"Link","bounds":[188,112,43,30],"objref":"7582","action":{"type":"GoTo","page":1002,"zoom":"XYZ 766 650 0"}},{"type":"Link","bounds":[188,203,43,31],"objref":"7583","action":{"type":"GoTo","page":1012,"zoom":"XYZ 161 845 0"}},{"type":"Link","bounds":[188,261,43,29],"objref":"7584","action":{"type":"GoTo","page":1035,"zoom":"XYZ 765 776 0"}},{"type":"Link","bounds":[188,318,43,30],"objref":"7585","action":{"type":"GoTo","page":1044,"zoom":"XYZ 613 181 0"}},{"type":"Link","bounds":[188,409,43,31],"objref":"7586","action":{"type":"GoTo","page":1061,"zoom":"XYZ 656 398 0"}},{"type":"Link","bounds":[188,468,41,29],"objref":"7587","action":{"type":"GoTo","page":1063,"zoom":"XYZ 370 891 0"}},{"type":"Link","bounds":[188,524,43,31],"objref":"7588","action":{"type":"GoTo","page":1063,"zoom":"XYZ 635 891 0"}},{"type":"Link","bounds":[188,582,43,29],"objref":"7589","action":{"type":"GoTo","page":1145,"zoom":"XYZ 427 1097 0"}},{"type":"Link","bounds":[188,639,43,30],"objref":"7590","action":{"type":"GoTo","page":1148,"zoom":"XYZ 365 902 0"}},{"type":"Link","bounds":[188,697,43,29],"objref":"7591","action":{"type":"GoTo","page":1149,"zoom":"XYZ 702 696 0"}},{"type":"Link","bounds":[188,753,43,31],"objref":"7592","action":{"type":"GoTo","page":1149,"zoom":"XYZ 266 627 0"}},{"type":"Link","bounds":[188,811,43,29],"objref":"7593","action":{"type":"GoTo","page":1151,"zoom":"XYZ 753 444 0"}},{"type":"Link","bounds":[188,903,43,29],"objref":"7594","action":{"type":"GoTo","page":1152,"zoom":"XYZ 531 1097 0"}},{"type":"Link","bounds":[188,959,43,31],"objref":"7595","action":{"type":"GoTo","page":1154,"zoom":"XYZ 773 948 0"}},{"type":"Link","bounds":[188,1018,43,29],"objref":"7596","action":{"type":"GoTo","page":1155,"zoom":"XYZ 442 478 0"}}]},{"page":1164,"annotations":[{"type":"Link","bounds":[736,112,43,30],"objref":"5760","action":{"type":"GoTo","page":1421,"zoom":"XYZ 116 802 0"}},{"type":"Link","bounds":[733,914,43,30],"objref":"5761","action":{"type":"GoTo","page":1421,"zoom":"XYZ 116 744 0"}},{"type":"Link","bounds":[710,982,43,31],"objref":"5762","action":{"type":"GoTo","page":1421,"zoom":"XYZ 116 687 0"}},{"type":"Link","bounds":[529,1051,42,31],"objref":"5763","action":{"type":"GoTo","page":1421,"zoom":"XYZ 116 630 0"}}]},{"page":1421,"annotations":[{"type":"Link","bounds":[188,112,40,30],"objref":"7599","action":{"type":"GoTo","page":1156,"zoom":"XYZ 309 868 0"}},{"type":"Link","bounds":[188,203,43,31],"objref":"7600","action":{"type":"GoTo","page":1157,"zoom":"XYZ 625 238 0"}},{"type":"Link","bounds":[188,261,43,29],"objref":"7601","action":{"type":"GoTo","page":1162,"zoom":"XYZ 698 295 0"}},{"type":"Link","bounds":[188,318,43,30],"objref":"7602","action":{"type":"GoTo","page":1163,"zoom":"XYZ 271 513 0"}},{"type":"Link","bounds":[188,409,43,31],"objref":"7603","action":{"type":"GoTo","page":1164,"zoom":"XYZ 736 1097 0"}},{"type":"Link","bounds":[188,468,43,29],"objref":"7604","action":{"type":"GoTo","page":1164,"zoom":"XYZ 732 295 0"}},{"type":"Link","bounds":[188,524,41,31],"objref":"7605","action":{"type":"GoTo","page":1164,"zoom":"XYZ 710 226 0"}},{"type":"Link","bounds":[188,582,43,29],"objref":"7606","action":{"type":"GoTo","page":1164,"zoom":"XYZ 528 158 0"}},{"type":"Link","bounds":[188,674,43,29],"objref":"7607","action":{"type":"GoTo","page":1167,"zoom":"XYZ 177 433 0"}},{"type":"Link","bounds":[188,730,43,31],"objref":"7608","action":{"type":"GoTo","page":1170,"zoom":"XYZ 470 845 0"}},{"type":"Link","bounds":[188,788,41,29],"objref":"7609","action":{"type":"GoTo","page":1170,"zoom":"XYZ 406 238 0"}},{"type":"Link","bounds":[188,914,43,30],"objref":"7610","action":{"type":"GoTo","page":1178,"zoom":"XYZ 558 364 0"}},{"type":"Link","bounds":[188,972,43,29],"objref":"7611","action":{"type":"GoTo","page":1206,"zoom":"XYZ 602 512 0"}},{"type":"Link","bounds":[188,1028,40,31],"objref":"7612","action":{"type":"GoTo","page":1207,"zoom":"XYZ 268 868 0"}}]},{"page":1422,"annotations":[{"type":"Link","bounds":[188,203,43,31],"objref":"7615","action":{"type":"GoTo","page":1212,"zoom":"XYZ 376 203 0"}},{"type":"Link","bounds":[188,261,40,29],"objref":"7616","action":{"type":"GoTo","page":1212,"zoom":"XYZ 289 169 0"}},{"type":"Link","bounds":[188,318,43,30],"objref":"7617","action":{"type":"GoTo","page":1213,"zoom":"XYZ 368 1097 0"}},{"type":"Link","bounds":[188,376,43,29],"objref":"7618","action":{"type":"GoTo","page":1213,"zoom":"XYZ 594 226 0"}},{"type":"Link","bounds":[188,432,43,31],"objref":"7619","action":{"type":"GoTo","page":1232,"zoom":"XYZ 374 685 0"}},{"type":"Link","bounds":[188,490,43,29],"objref":"7620","action":{"type":"GoTo","page":1242,"zoom":"XYZ 344 753 0"}},{"type":"Link","bounds":[188,547,41,31],"objref":"7621","action":{"type":"GoTo","page":1245,"zoom":"XYZ 146 375 0"}},{"type":"Link","bounds":[188,605,43,29],"objref":"7622","action":{"type":"GoTo","page":1247,"zoom":"XYZ 737 719 0"}},{"type":"Link","bounds":[188,662,43,30],"objref":"7623","action":{"type":"GoTo","page":1303,"zoom":"XYZ 342 994 0"}},{"type":"Link","bounds":[188,788,43,29],"objref":"7624","action":{"type":"GoTo","page":1322,"zoom":"XYZ 473 238 0"}},{"type":"Link","bounds":[188,845,43,30],"objref":"7625","action":{"type":"GoTo","page":1323,"zoom":"XYZ 766 203 0"}}]},{"page":1423,"annotations":[{"type":"Link","bounds":[163,280,450,26],"objref":"8022","action":{"type":"GoTo","page":7,"zoom":"XYZ 116 1017 0"}},{"type":"Link","bounds":[163,307,138,26],"objref":"8023","action":{"type":"GoTo","page":26,"zoom":"XYZ 116 1017 0"}},{"type":"Link","bounds":[163,335,77,26],"objref":"8024","action":{"type":"GoTo","page":29,"zoom":"XYZ 116 1100 0"}},{"type":"Link","bounds":[209,362,416,26],"objref":"8025","action":{"type":"GoTo","page":31,"zoom":"XYZ 116 1100 0"}},{"type":"Link","bounds":[255,390,396,26],"objref":"8026","action":{"type":"GoTo","page":33,"zoom":"XYZ 116 962 0"}},{"type":"Link","bounds":[255,417,376,26],"objref":"8027","action":{"type":"GoTo","page":37,"zoom":"XYZ 116 423 0"}},{"type":"Link","bounds":[255,445,520,26],"objref":"8028","action":{"type":"GoTo","page":41,"zoom":"XYZ 116 309 0"}},{"type":"Link","bounds":[255,472,431,26],"objref":"8029","action":{"type":"GoTo","page":50,"zoom":"XYZ 116 859 0"}},{"type":"Link","bounds":[255,500,225,26],"objref":"8030","action":{"type":"GoTo","page":61,"zoom":"XYZ 116 527 0"}},{"type":"Link","bounds":[209,527,494,26],"objref":"8031","action":{"type":"GoTo","page":75,"zoom":"XYZ 116 1100 0"}},{"type":"Link","bounds":[255,555,159,26],"objref":"8032","action":{"type":"GoTo","page":77,"zoom":"XYZ 116 962 0"}},{"type":"Link","bounds":[255,582,150,26],"objref":"8033","action":{"type":"GoTo","page":85,"zoom":"XYZ 116 859 0"}},{"type":"Link","bounds":[255,610,399,26],"objref":"8034","action":{"type":"GoTo","page":98,"zoom":"XYZ 116 492 0"}},{"type":"Link","bounds":[255,637,275,26],"objref":"8035","action":{"type":"GoTo","page":111,"zoom":"XYZ 116 1100 0"}},{"type":"Link","bounds":[255,665,381,26],"objref":"8036","action":{"type":"GoTo","page":123,"zoom":"XYZ 116 802 0"}},{"type":"Link","bounds":[255,692,507,54],"objref":"8037","action":{"type":"GoTo","page":137,"zoom":"XYZ 116 893 0"}},{"type":"Link","bounds":[255,747,393,26],"objref":"8038","action":{"type":"GoTo","page":153,"zoom":"XYZ 116 584 0"}},{"type":"Link","bounds":[255,775,196,26],"objref":"8039","action":{"type":"GoTo","page":168,"zoom":"XYZ 116 698 0"}},{"type":"Link","bounds":[209,802,419,26],"objref":"8040","action":{"type":"GoTo","page":183,"zoom":"XYZ 116 1100 0"}},{"type":"Link","bounds":[255,830,321,26],"objref":"8041","action":{"type":"GoTo","page":185,"zoom":"XYZ 116 962 0"}},{"type":"Link","bounds":[255,857,352,26],"objref":"8042","action":{"type":"GoTo","page":192,"zoom":"XYZ 116 343 0"}},{"type":"Link","bounds":[255,885,553,53],"objref":"8043","action":{"type":"GoTo","page":198,"zoom":"XYZ 116 458 0"}},{"type":"Link","bounds":[255,940,550,53],"objref":"8044","action":{"type":"GoTo","page":212,"zoom":"XYZ 116 893 0"}},{"type":"Link","bounds":[255,995,541,53],"objref":"8045","action":{"type":"GoTo","page":223,"zoom":"XYZ 116 664 0"}},{"type":"Link","bounds":[255,1050,190,26],"objref":"8046","action":{"type":"GoTo","page":237,"zoom":"XYZ 116 744 0"}}]},{"page":1167,"annotations":[{"type":"Link","bounds":[179,776,43,31],"objref":"5770","action":{"type":"GoTo","page":1421,"zoom":"XYZ 116 538 0"}}]},{"page":143,"annotations":[{"type":"Link","bounds":[448,547,33,31],"objref":"1171","action":{"type":"GoTo","page":1410,"zoom":"XYZ 116 698 0"}}]},{"page":1424,"annotations":[{"type":"Link","bounds":[255,110,255,26],"objref":"8049","action":{"type":"GoTo","page":245,"zoom":"XYZ 116 893 0"}},{"type":"Link","bounds":[255,138,350,25],"objref":"8050","action":{"type":"GoTo","page":253,"zoom":"XYZ 116 412 0"}},{"type":"Link","bounds":[255,165,335,26],"objref":"8051","action":{"type":"GoTo","page":266,"zoom":"XYZ 116 893 0"}},{"type":"Link","bounds":[255,193,261,25],"objref":"8052","action":{"type":"GoTo","page":276,"zoom":"XYZ 116 767 0"}},{"type":"Link","bounds":[255,220,440,26],"objref":"8053","action":{"type":"GoTo","page":294,"zoom":"XYZ 116 1100 0"}},{"type":"Link","bounds":[163,248,85,25],"objref":"8054","action":{"type":"GoTo","page":306,"zoom":"XYZ 116 1100 0"}},{"type":"Link","bounds":[209,275,185,26],"objref":"8055","action":{"type":"GoTo","page":308,"zoom":"XYZ 116 1100 0"}},{"type":"Link","bounds":[255,303,187,25],"objref":"8056","action":{"type":"GoTo","page":310,"zoom":"XYZ 116 962 0"}},{"type":"Link","bounds":[255,330,132,26],"objref":"8057","action":{"type":"GoTo","page":325,"zoom":"XYZ 116 355 0"}},{"type":"Link","bounds":[255,358,350,25],"objref":"8058","action":{"type":"GoTo","page":333,"zoom":"XYZ 116 676 0"}},{"type":"Link","bounds":[255,385,321,26],"objref":"8059","action":{"type":"GoTo","page":340,"zoom":"XYZ 116 286 0"}},{"type":"Link","bounds":[255,413,394,25],"objref":"8060","action":{"type":"GoTo","page":351,"zoom":"XYZ 116 561 0"}},{"type":"Link","bounds":[255,440,449,26],"objref":"8061","action":{"type":"GoTo","page":369,"zoom":"XYZ 116 1100 0"}},{"type":"Link","bounds":[255,468,345,25],"objref":"8062","action":{"type":"GoTo","page":381,"zoom":"XYZ 116 550 0"}},{"type":"Link","bounds":[209,495,294,26],"objref":"8063","action":{"type":"GoTo","page":397,"zoom":"XYZ 116 1100 0"}},{"type":"Link","bounds":[255,523,125,25],"objref":"8064","action":{"type":"GoTo","page":399,"zoom":"XYZ 116 962 0"}},{"type":"Link","bounds":[255,550,417,26],"objref":"8065","action":{"type":"GoTo","page":417,"zoom":"XYZ 116 1100 0"}},{"type":"Link","bounds":[255,578,362,25],"objref":"8066","action":{"type":"GoTo","page":427,"zoom":"XYZ 116 458 0"}},{"type":"Link","bounds":[255,605,141,26],"objref":"8067","action":{"type":"GoTo","page":443,"zoom":"XYZ 116 1100 0"}},{"type":"Link","bounds":[255,633,376,25],"objref":"8068","action":{"type":"GoTo","page":460,"zoom":"XYZ 116 893 0"}},{"type":"Link","bounds":[255,660,268,26],"objref":"8069","action":{"type":"GoTo","page":492,"zoom":"XYZ 116 825 0"}},{"type":"Link","bounds":[255,688,559,53],"objref":"8070","action":{"type":"GoTo","page":508,"zoom":"XYZ 116 687 0"}},{"type":"Link","bounds":[209,743,329,25],"objref":"8071","action":{"type":"GoTo","page":521,"zoom":"XYZ 116 1100 0"}},{"type":"Link","bounds":[255,770,520,53],"objref":"8072","action":{"type":"GoTo","page":523,"zoom":"XYZ 116 962 0"}},{"type":"Link","bounds":[255,825,535,53],"objref":"8073","action":{"type":"GoTo","page":529,"zoom":"XYZ 116 446 0"}},{"type":"Link","bounds":[255,880,559,53],"objref":"8074","action":{"type":"GoTo","page":573,"zoom":"XYZ 116 825 0"}},{"type":"Link","bounds":[163,935,92,26],"objref":"8075","action":{"type":"GoTo","page":595,"zoom":"XYZ 116 1100 0"}},{"type":"Link","bounds":[209,963,118,25],"objref":"8076","action":{"type":"GoTo","page":597,"zoom":"XYZ 116 1100 0"}},{"type":"Link","bounds":[255,990,179,26],"objref":"8077","action":{"type":"GoTo","page":599,"zoom":"XYZ 116 962 0"}},{"type":"Link","bounds":[255,1018,283,25],"objref":"8078","action":{"type":"GoTo","page":616,"zoom":"XYZ 116 229 0"}},{"type":"Link","bounds":[255,1045,183,26],"objref":"8079","action":{"type":"GoTo","page":626,"zoom":"XYZ 116 859 0"}},{"type":"Link","bounds":[255,1073,323,25],"objref":"8080","action":{"type":"GoTo","page":654,"zoom":"XYZ 116 366 0"}}]},{"page":656,"annotations":[{"type":"Link","bounds":[538,376,40,29],"objref":"3664","action":{"type":"GoTo","page":1417,"zoom":"XYZ 116 160 0"}}]},{"page":400,"annotations":[{"type":"Link","bounds":[464,834,34,31],"objref":"2566","action":{"type":"GoTo","page":1414,"zoom":"XYZ 116 217 0"}}]},{"page":144,"annotations":[{"type":"Link","bounds":[333,926,32,29],"objref":"1174","action":{"type":"GoTo","page":1410,"zoom":"XYZ 116 504 0"}}]},{"page":1425,"annotations":[{"type":"Link","bounds":[209,110,204,26],"objref":"8083","action":{"type":"GoTo","page":662,"zoom":"XYZ 116 1100 0"}},{"type":"Link","bounds":[255,138,232,25],"objref":"8084","action":{"type":"GoTo","page":664,"zoom":"XYZ 116 962 0"}},{"type":"Link","bounds":[255,165,122,26],"objref":"8085","action":{"type":"GoTo","page":679,"zoom":"XYZ 116 561 0"}},{"type":"Link","bounds":[255,193,138,25],"objref":"8086","action":{"type":"GoTo","page":690,"zoom":"XYZ 116 893 0"}},{"type":"Link","bounds":[255,220,225,26],"objref":"8087","action":{"type":"GoTo","page":708,"zoom":"XYZ 116 1100 0"}},{"type":"Link","bounds":[255,248,329,25],"objref":"8088","action":{"type":"GoTo","page":716,"zoom":"XYZ 116 1100 0"}},{"type":"Link","bounds":[255,275,254,26],"objref":"8089","action":{"type":"GoTo","page":742,"zoom":"XYZ 116 893 0"}},{"type":"Link","bounds":[255,303,303,25],"objref":"8090","action":{"type":"GoTo","page":755,"zoom":"XYZ 116 320 0"}},{"type":"Link","bounds":[255,330,202,26],"objref":"8091","action":{"type":"GoTo","page":785,"zoom":"XYZ 116 584 0"}},{"type":"Link","bounds":[209,358,297,25],"objref":"8092","action":{"type":"GoTo","page":808,"zoom":"XYZ 116 1100 0"}},{"type":"Link","bounds":[255,385,561,53],"objref":"8093","action":{"type":"GoTo","page":810,"zoom":"XYZ 116 962 0"}},{"type":"Link","bounds":[255,440,142,26],"objref":"8094","action":{"type":"GoTo","page":820,"zoom":"XYZ 116 1100 0"}},{"type":"Link","bounds":[255,468,536,25],"objref":"8095","action":{"type":"GoTo","page":828,"zoom":"XYZ 116 595 0"}},{"type":"Link","bounds":[255,495,283,26],"objref":"8096","action":{"type":"GoTo","page":843,"zoom":"XYZ 116 1100 0"}},{"type":"Link","bounds":[255,523,266,25],"objref":"8097","action":{"type":"GoTo","page":855,"zoom":"XYZ 116 1100 0"}},{"type":"Link","bounds":[255,550,385,26],"objref":"8098","action":{"type":"GoTo","page":874,"zoom":"XYZ 116 1100 0"}},{"type":"Link","bounds":[255,578,356,25],"objref":"8099","action":{"type":"GoTo","page":887,"zoom":"XYZ 116 1100 0"}},{"type":"Link","bounds":[255,605,472,26],"objref":"8100","action":{"type":"GoTo","page":906,"zoom":"XYZ 116 1100 0"}},{"type":"Link","bounds":[255,633,269,25],"objref":"8101","action":{"type":"GoTo","page":920,"zoom":"XYZ 116 859 0"}},{"type":"Link","bounds":[163,660,92,26],"objref":"8102","action":{"type":"GoTo","page":927,"zoom":"XYZ 116 1100 0"}},{"type":"Link","bounds":[209,688,281,25],"objref":"8103","action":{"type":"GoTo","page":929,"zoom":"XYZ 116 1100 0"}},{"type":"Link","bounds":[255,715,228,26],"objref":"8104","action":{"type":"GoTo","page":931,"zoom":"XYZ 116 962 0"}},{"type":"Link","bounds":[255,743,141,25],"objref":"8105","action":{"type":"GoTo","page":937,"zoom":"XYZ 116 320 0"}},{"type":"Link","bounds":[255,770,183,26],"objref":"8106","action":{"type":"GoTo","page":947,"zoom":"XYZ 116 893 0"}},{"type":"Link","bounds":[255,798,119,25],"objref":"8107","action":{"type":"GoTo","page":962,"zoom":"XYZ 116 1100 0"}},{"type":"Link","bounds":[255,825,269,26],"objref":"8108","action":{"type":"GoTo","page":973,"zoom":"XYZ 116 1100 0"}},{"type":"Link","bounds":[255,853,219,25],"objref":"8109","action":{"type":"GoTo","page":997,"zoom":"XYZ 116 561 0"}},{"type":"Link","bounds":[255,880,136,26],"objref":"8110","action":{"type":"GoTo","page":1009,"zoom":"XYZ 116 1100 0"}},{"type":"Link","bounds":[209,908,399,25],"objref":"8111","action":{"type":"GoTo","page":1016,"zoom":"XYZ 116 1100 0"}},{"type":"Link","bounds":[255,935,232,26],"objref":"8112","action":{"type":"GoTo","page":1018,"zoom":"XYZ 116 962 0"}},{"type":"Link","bounds":[255,963,187,25],"objref":"8113","action":{"type":"GoTo","page":1032,"zoom":"XYZ 116 561 0"}},{"type":"Link","bounds":[255,990,187,26],"objref":"8114","action":{"type":"GoTo","page":1046,"zoom":"XYZ 116 263 0"}},{"type":"Link","bounds":[255,1018,272,25],"objref":"8115","action":{"type":"GoTo","page":1058,"zoom":"XYZ 116 767 0"}},{"type":"Link","bounds":[255,1045,436,26],"objref":"8116","action":{"type":"GoTo","page":1080,"zoom":"XYZ 116 1100 0"}}]},{"page":401,"annotations":[{"type":"Link","bounds":[353,307,34,29],"objref":"2569","action":{"type":"GoTo","page":1414,"zoom":"XYZ 116 160 0"}}]},{"page":1426,"annotations":[{"type":"Link","bounds":[255,110,425,53],"objref":"8119","action":{"type":"GoTo","page":1090,"zoom":"XYZ 116 492 0"}},{"type":"Link","bounds":[255,165,501,26],"objref":"8120","action":{"type":"GoTo","page":1105,"zoom":"XYZ 116 893 0"}},{"type":"Link","bounds":[255,193,553,53],"objref":"8121","action":{"type":"GoTo","page":1119,"zoom":"XYZ 116 825 0"}},{"type":"Link","bounds":[255,248,422,53],"objref":"8122","action":{"type":"GoTo","page":1143,"zoom":"XYZ 116 412 0"}},{"type":"Link","bounds":[255,303,208,25],"objref":"8123","action":{"type":"GoTo","page":1171,"zoom":"XYZ 116 286 0"}},{"type":"Link","bounds":[209,330,362,26],"objref":"8124","action":{"type":"GoTo","page":1181,"zoom":"XYZ 116 1100 0"}},{"type":"Link","bounds":[255,358,220,25],"objref":"8125","action":{"type":"GoTo","page":1183,"zoom":"XYZ 116 962 0"}},{"type":"Link","bounds":[255,385,466,26],"objref":"8126","action":{"type":"GoTo","page":1192,"zoom":"XYZ 116 527 0"}},{"type":"Link","bounds":[255,413,497,25],"objref":"8127","action":{"type":"GoTo","page":1206,"zoom":"XYZ 116 561 0"}},{"type":"Link","bounds":[255,440,379,26],"objref":"8128","action":{"type":"GoTo","page":1214,"zoom":"XYZ 116 859 0"}},{"type":"Link","bounds":[255,468,225,25],"objref":"8129","action":{"type":"GoTo","page":1227,"zoom":"XYZ 116 332 0"}},{"type":"Link","bounds":[255,495,558,53],"objref":"8130","action":{"type":"GoTo","page":1242,"zoom":"XYZ 116 1100 0"}},{"type":"Link","bounds":[255,550,271,26],"objref":"8131","action":{"type":"GoTo","page":1256,"zoom":"XYZ 116 893 0"}},{"type":"Link","bounds":[255,578,312,25],"objref":"8132","action":{"type":"GoTo","page":1263,"zoom":"XYZ 116 630 0"}},{"type":"Link","bounds":[255,605,543,53],"objref":"8133","action":{"type":"GoTo","page":1276,"zoom":"XYZ 116 790 0"}},{"type":"Link","bounds":[255,660,403,26],"objref":"8134","action":{"type":"GoTo","page":1293,"zoom":"XYZ 116 446 0"}},{"type":"Link","bounds":[255,688,463,25],"objref":"8135","action":{"type":"GoTo","page":1299,"zoom":"XYZ 116 595 0"}},{"type":"Link","bounds":[255,715,368,26],"objref":"8136","action":{"type":"GoTo","page":1308,"zoom":"XYZ 116 1100 0"}},{"type":"Link","bounds":[255,743,373,25],"objref":"8137","action":{"type":"GoTo","page":1318,"zoom":"XYZ 116 458 0"}},{"type":"Link","bounds":[255,770,362,26],"objref":"8138","action":{"type":"GoTo","page":1329,"zoom":"XYZ 116 412 0"}},{"type":"Link","bounds":[163,798,115,25],"objref":"8139","action":{"type":"GoTo","page":1340,"zoom":"XYZ 116 1100 0"}},{"type":"Link","bounds":[209,825,242,26],"objref":"8140","action":{"type":"GoTo","page":1342,"zoom":"XYZ 116 962 0"}},{"type":"Link","bounds":[209,853,543,25],"objref":"8141","action":{"type":"GoTo","page":1350,"zoom":"XYZ 116 1100 0"}},{"type":"Link","bounds":[209,880,518,26],"objref":"8142","action":{"type":"GoTo","page":1362,"zoom":"XYZ 116 1100 0"}},{"type":"Link","bounds":[163,908,98,25],"objref":"8143","action":{"type":"GoTo","page":1377,"zoom":"XYZ 116 1100 0"}},{"type":"Link","bounds":[209,935,604,26],"objref":"8144","action":{"type":"GoTo","page":1379,"zoom":"XYZ 116 1017 0"}},{"type":"Link","bounds":[209,963,500,25],"objref":"8145","action":{"type":"GoTo","page":1398,"zoom":"XYZ 116 1017 0"}},{"type":"Link","bounds":[163,990,91,26],"objref":"8146","action":{"type":"GoTo","page":1406,"zoom":"XYZ 116 1017 0"}}]},{"page":1170,"annotations":[{"type":"Link","bounds":[471,364,42,30],"objref":"5777","action":{"type":"GoTo","page":1421,"zoom":"XYZ 116 481 0"}},{"type":"Link","bounds":[408,972,41,29],"objref":"5778","action":{"type":"GoTo","page":1421,"zoom":"XYZ 116 423 0"}}]},{"page":149,"annotations":[{"type":"Link","bounds":[701,513,34,29],"objref":"1185","action":{"type":"GoTo","page":1410,"zoom":"XYZ 116 412 0"}}]},{"page":151,"annotations":[{"type":"Link","bounds":[545,995,36,29],"objref":"1190","action":{"type":"GoTo","page":1410,"zoom":"XYZ 116 217 0"}}]},{"page":409,"annotations":[{"type":"Link","bounds":[313,1018,34,29],"objref":"2586","action":{"type":"GoTo","page":1415,"zoom":"XYZ 116 1100 0"}}]},{"page":1178,"annotations":[{"type":"Link","bounds":[558,845,44,30],"objref":"5795","action":{"type":"GoTo","page":1421,"zoom":"XYZ 116 297 0"}}]},{"page":666,"annotations":[{"type":"Link","bounds":[403,1040,40,29],"objref":"3915","action":{"type":"GoTo","page":1418,"zoom":"XYZ 116 1100 0"}}]},{"page":924,"annotations":[{"type":"Link","bounds":[590,238,41,29],"objref":"4749","action":{"type":"GoTo","page":1419,"zoom":"XYZ 116 572 0"}}]},{"page":672,"annotations":[{"type":"Link","bounds":[223,730,40,31],"objref":"3930","action":{"type":"GoTo","page":1418,"zoom":"XYZ 116 1042 0"}}]},{"page":416,"annotations":[{"type":"Link","bounds":[545,147,36,29],"objref":"2601","action":{"type":"GoTo","page":1415,"zoom":"XYZ 116 1042 0"}}]},{"page":673,"annotations":[{"type":"Link","bounds":[322,180,40,31],"objref":"3933","action":{"type":"GoTo","page":1418,"zoom":"XYZ 116 985 0"}}]},{"page":931,"annotations":[{"type":"Link","bounds":[720,678,42,31],"objref":"5027","action":{"type":"GoTo","page":1419,"zoom":"XYZ 116 515 0"}}]},{"page":169,"annotations":[{"type":"Link","bounds":[588,743,34,29],"objref":"1227","action":{"type":"GoTo","page":1411,"zoom":"XYZ 116 1100 0"}}]},{"page":175,"annotations":[{"type":"Link","bounds":[293,215,35,29],"objref":"1240","action":{"type":"GoTo","page":1411,"zoom":"XYZ 116 1008 0"}},{"type":"Link","bounds":[588,628,34,29],"objref":"1241","action":{"type":"GoTo","page":1411,"zoom":"XYZ 116 951 0"}},{"type":"Link","bounds":[697,662,33,30],"objref":"1242","action":{"type":"GoTo","page":1411,"zoom":"XYZ 116 859 0"}},{"type":"Link","bounds":[258,697,34,29],"objref":"1243","action":{"type":"GoTo","page":1411,"zoom":"XYZ 116 767 0"}}]},{"page":432,"annotations":[{"type":"Link","bounds":[361,707,33,31],"objref":"2636","action":{"type":"GoTo","page":1415,"zoom":"XYZ 116 985 0"}}]},{"page":176,"annotations":[{"type":"Link","bounds":[345,524,34,31],"objref":"1246","action":{"type":"GoTo","page":1411,"zoom":"XYZ 116 710 0"}}]},{"page":434,"annotations":[{"type":"Link","bounds":[167,112,33,30],"objref":"2641","action":{"type":"GoTo","page":1415,"zoom":"XYZ 116 893 0"}}]},{"page":178,"annotations":[{"type":"Link","bounds":[228,249,32,31],"objref":"1251","action":{"type":"GoTo","page":1411,"zoom":"XYZ 116 618 0"}},{"type":"Link","bounds":[159,880,32,29],"objref":"1252","action":{"type":"GoTo","page":1411,"zoom":"XYZ 116 561 0"}}]},{"page":948,"annotations":[{"type":"Link","bounds":[440,1005,43,31],"objref":"5062","action":{"type":"GoTo","page":1419,"zoom":"XYZ 116 423 0"}}]},{"page":1206,"annotations":[{"type":"Link","bounds":[603,698,75,32],"objref":"6168","action":{"type":"GoTo","page":1421,"zoom":"XYZ 116 240 0"}}]},{"page":1207,"annotations":[{"type":"Link","bounds":[269,341,41,30],"objref":"6172","action":{"type":"GoTo","page":1421,"zoom":"XYZ 116 183 0"}}]},{"page":443,"annotations":[{"type":"Link","bounds":[434,414,34,31],"objref":"2660","action":{"type":"GoTo","page":1415,"zoom":"XYZ 116 767 0"}}]},{"page":1212,"annotations":[{"type":"Link","bounds":[379,1005,41,31],"objref":"6183","action":{"type":"GoTo","page":1422,"zoom":"XYZ 116 1008 0"}},{"type":"Link","bounds":[290,1040,42,29],"objref":"6184","action":{"type":"GoTo","page":1422,"zoom":"XYZ 116 951 0"}}]},{"page":700,"annotations":[{"type":"Link","bounds":[286,284,42,29],"objref":"3988","action":{"type":"GoTo","page":1418,"zoom":"XYZ 116 928 0"}}]},{"page":1213,"annotations":[{"type":"Link","bounds":[370,112,43,30],"objref":"6187","action":{"type":"GoTo","page":1422,"zoom":"XYZ 116 893 0"}},{"type":"Link","bounds":[594,982,43,31],"objref":"6188","action":{"type":"GoTo","page":1422,"zoom":"XYZ 116 836 0"}}]},{"page":703,"annotations":[{"type":"Link","bounds":[741,684,41,31],"objref":"3995","action":{"type":"GoTo","page":1418,"zoom":"XYZ 116 870 0"}}]},{"page":193,"annotations":[{"type":"Link","bounds":[782,112,35,30],"objref":"1549","action":{"type":"GoTo","page":1411,"zoom":"XYZ 116 332 0"}}]},{"page":451,"annotations":[{"type":"Link","bounds":[220,215,34,29],"objref":"2677","action":{"type":"GoTo","page":1415,"zoom":"XYZ 116 676 0"}}]},{"page":453,"annotations":[{"type":"Link","bounds":[284,112,34,30],"objref":"2682","action":{"type":"GoTo","page":1415,"zoom":"XYZ 116 584 0"}},{"type":"Link","bounds":[333,180,32,31],"objref":"2683","action":{"type":"GoTo","page":1415,"zoom":"XYZ 116 492 0"}}]},{"page":203,"annotations":[{"type":"Link","bounds":[555,593,32,30],"objref":"1572","action":{"type":"GoTo","page":1411,"zoom":"XYZ 116 275 0"}},{"type":"Link","bounds":[405,697,33,29],"objref":"1573","action":{"type":"GoTo","page":1411,"zoom":"XYZ 116 217 0"}}]},{"page":460,"annotations":[{"type":"Link","bounds":[663,758,32,30],"objref":"2698","action":{"type":"GoTo","page":1415,"zoom":"XYZ 116 435 0"}},{"type":"Link","bounds":[193,930,33,29],"objref":"2699","action":{"type":"GoTo","page":1415,"zoom":"XYZ 116 378 0"}}]},{"page":204,"annotations":[{"type":"Link","bounds":[603,501,34,31],"objref":"1577","action":{"type":"GoTo","page":1412,"zoom":"XYZ 116 1100 0"}}]},{"page":461,"annotations":[{"type":"Link","bounds":[380,799,34,31],"objref":"2702","action":{"type":"GoTo","page":1415,"zoom":"XYZ 116 286 0"}}]},{"page":206,"annotations":[{"type":"Link","bounds":[721,674,34,29],"objref":"1582","action":{"type":"GoTo","page":1412,"zoom":"XYZ 116 1008 0"}}]},{"page":207,"annotations":[{"type":"Link","bounds":[633,490,33,29],"objref":"1585","action":{"type":"GoTo","page":1412,"zoom":"XYZ 116 916 0"}},{"type":"Link","bounds":[469,834,34,29],"objref":"1586","action":{"type":"GoTo","page":1412,"zoom":"XYZ 116 824 0"}},{"type":"Link","bounds":[617,1028,32,31],"objref":"1587","action":{"type":"GoTo","page":1412,"zoom":"XYZ 116 767 0"}}]},{"page":1232,"annotations":[{"type":"Link","bounds":[374,524,43,31],"objref":"6229","action":{"type":"GoTo","page":1422,"zoom":"XYZ 116 779 0"}}]},{"page":464,"annotations":[{"type":"Link","bounds":[199,147,33,29],"objref":"2709","action":{"type":"GoTo","page":1415,"zoom":"XYZ 116 229 0"}},{"type":"Link","bounds":[764,662,32,30],"objref":"2710","action":{"type":"GoTo","page":1416,"zoom":"XYZ 116 1100 0"}}]},{"page":208,"annotations":[{"type":"Link","bounds":[209,215,34,29],"objref":"1591","action":{"type":"GoTo","page":1412,"zoom":"XYZ 116 607 0"}},{"type":"Link","bounds":[484,468,34,29],"objref":"1592","action":{"type":"GoTo","page":1412,"zoom":"XYZ 116 515 0"}},{"type":"Link","bounds":[513,834,34,29],"objref":"1593","action":{"type":"GoTo","page":1412,"zoom":"XYZ 116 423 0"}}]},{"page":209,"annotations":[{"type":"Link","bounds":[380,765,33,31],"objref":"1596","action":{"type":"GoTo","page":1412,"zoom":"XYZ 116 263 0"}}]},{"page":466,"annotations":[{"type":"Link","bounds":[347,822,41,31],"objref":"2715","action":{"type":"GoTo","page":1416,"zoom":"XYZ 116 1008 0"}}]},{"page":210,"annotations":[{"type":"Link","bounds":[376,445,33,29],"objref":"1599","action":{"type":"GoTo","page":1412,"zoom":"XYZ 116 171 0"}},{"type":"Link","bounds":[782,891,32,30],"objref":"1600","action":{"type":"GoTo","page":1413,"zoom":"XYZ 116 1100 0"}}]},{"page":211,"annotations":[{"type":"Link","bounds":[633,707,33,31],"objref":"1603","action":{"type":"GoTo","page":1413,"zoom":"XYZ 116 1042 0"}}]},{"page":213,"annotations":[{"type":"Link","bounds":[636,799,35,31],"objref":"1608","action":{"type":"GoTo","page":1413,"zoom":"XYZ 116 847 0"}}]},{"page":726,"annotations":[{"type":"Link","bounds":[773,743,43,29],"objref":"4042","action":{"type":"GoTo","page":1418,"zoom":"XYZ 116 710 0"}}]},{"page":1242,"annotations":[{"type":"Link","bounds":[345,455,43,31],"objref":"6250","action":{"type":"GoTo","page":1422,"zoom":"XYZ 116 721 0"}}]},{"page":474,"annotations":[{"type":"Link","bounds":[471,284,42,29],"objref":"2732","action":{"type":"GoTo","page":1416,"zoom":"XYZ 116 916 0"}}]},{"page":1245,"annotations":[{"type":"Link","bounds":[148,834,41,29],"objref":"6257","action":{"type":"GoTo","page":1422,"zoom":"XYZ 116 664 0"}}]},{"page":990,"annotations":[{"type":"Link","bounds":[588,341,43,30],"objref":"5148","action":{"type":"GoTo","page":1419,"zoom":"XYZ 116 297 0"}}]},{"page":1247,"annotations":[{"type":"Link","bounds":[738,490,43,29],"objref":"6262","action":{"type":"GoTo","page":1422,"zoom":"XYZ 116 607 0"}}]},{"page":483,"annotations":[{"type":"Link","bounds":[141,284,42,29],"objref":"2751","action":{"type":"GoTo","page":1416,"zoom":"XYZ 116 825 0"}},{"type":"Link","bounds":[457,972,44,29],"objref":"2752","action":{"type":"GoTo","page":1416,"zoom":"XYZ 116 664 0"}}]},{"page":1001,"annotations":[{"type":"Link","bounds":[487,765,43,29],"objref":"5173","action":{"type":"GoTo","page":1419,"zoom":"XYZ 116 240 0"}}]},{"page":1002,"annotations":[{"type":"Link","bounds":[292,341,43,30],"objref":"5176","action":{"type":"GoTo","page":1419,"zoom":"XYZ 116 183 0"}},{"type":"Link","bounds":[768,559,42,29],"objref":"5177","action":{"type":"GoTo","page":1420,"zoom":"XYZ 116 1100 0"}}]},{"page":491,"annotations":[{"type":"Link","bounds":[603,318,43,30],"objref":"2769","action":{"type":"GoTo","page":1416,"zoom":"XYZ 116 572 0"}}]},{"page":239,"annotations":[{"type":"Link","bounds":[278,272,32,31],"objref":"1661","action":{"type":"GoTo","page":1413,"zoom":"XYZ 116 721 0"}},{"type":"Link","bounds":[196,845,33,30],"objref":"1662","action":{"type":"GoTo","page":1413,"zoom":"XYZ 116 664 0"}}]},{"page":241,"annotations":[{"type":"Link","bounds":[562,799,34,31],"objref":"1667","action":{"type":"GoTo","page":1413,"zoom":"XYZ 116 538 0"}}]},{"page":1012,"annotations":[{"type":"Link","bounds":[163,364,42,30],"objref":"5198","action":{"type":"GoTo","page":1420,"zoom":"XYZ 116 1008 0"}}]},{"page":756,"annotations":[{"type":"Link","bounds":[267,536,43,29],"objref":"4103","action":{"type":"GoTo","page":1418,"zoom":"XYZ 116 653 0"}}]},{"page":757,"annotations":[{"type":"Link","bounds":[640,364,43,30],"objref":"4106","action":{"type":"GoTo","page":1418,"zoom":"XYZ 116 595 0"}}]},{"page":763,"annotations":[{"type":"Link","bounds":[515,238,43,29],"objref":"4119","action":{"type":"GoTo","page":1418,"zoom":"XYZ 116 538 0"}},{"type":"Link","bounds":[328,880,42,29],"objref":"4120","action":{"type":"GoTo","page":1418,"zoom":"XYZ 116 481 0"}}]},{"page":764,"annotations":[{"type":"Link","bounds":[370,203,43,31],"objref":"4123","action":{"type":"GoTo","page":1418,"zoom":"XYZ 116 423 0"}}]},{"page":765,"annotations":[{"type":"Link","bounds":[255,937,43,30],"objref":"4126","action":{"type":"GoTo","page":1418,"zoom":"XYZ 116 332 0"}}]},{"page":767,"annotations":[{"type":"Link","bounds":[542,972,43,29],"objref":"4131","action":{"type":"GoTo","page":1418,"zoom":"XYZ 116 274 0"}}]},{"page":255,"annotations":[{"type":"Link","bounds":[515,914,33,30],"objref":"1696","action":{"type":"GoTo","page":1413,"zoom":"XYZ 116 481 0"}}]}]}